pynixf-0.1.0.dist-info/METADATA
pynixf-0.1.0.dist-info/WHEEL
nixf.cpython-312-x86_64-linux-gnu.so
pynixf-0.1.0.data/purelib/nixf.pyi
pynixf-0.1.0.dist-info/RECORD
