Metadata-Version: 2.1
Name: pynixf
Version: 0.1.0
Summary: Python bindings for libnixf
Requires-Python: >=3.12
